rohan_pristine/__init__.py
rohan_pristine/model.py
rohan_pristine/model_files/README.md
rohan_pristine/model_files/config.json
rohan_pristine/model_files/config_sentence_transformers.json
rohan_pristine/model_files/model.safetensors
rohan_pristine/model_files/modules.json
rohan_pristine/model_files/sentence_bert_config.json
rohan_pristine/model_files/special_tokens_map.json
rohan_pristine/model_files/tokenizer.json
rohan_pristine/model_files/tokenizer_config.json
rohan_pristine/model_files/vocab.txt
rohan_pristine-1.0.0.dist-info/METADATA
rohan_pristine-1.0.0.dist-info/WHEEL
rohan_pristine-1.0.0.dist-info/top_level.txt
rohan_pristine-1.0.0.dist-info/RECORD
